<Properties StartupConfiguration="{E8484693-2EE6-4C40-A383-9BEF691A10F4}|Default">
  <MonoDevelop.Ide.Workspace ActiveConfiguration="Debug" />
  <MultiItemStartupConfigurations />
  <MonoDevelop.Ide.ItemProperties.Lexoh.Droid PreferredExecutionTarget="Android.pixel_5_-_api_31" />
  <DisabledProjects>
    <String>iOS/Lexoh.iOS.csproj</String>
    <String>UITests/Lexoh.UITests.csproj</String>
  </DisabledProjects>
  <MonoDevelop.Ide.Workbench ActiveDocument="Droid/Lexoh.Droid.csproj">
    <Files>
      <File FileName="Droid/Lexoh.Droid.csproj" Line="37" Column="56" />
      <File FileName="Droid/MainActivity.cs" Line="31" Column="1" />
    </Files>
    <Pads>
      <Pad Id="ProjectPad">
        <State name="__root__">
          <Node name="LexohMobile" expanded="True">
            <Node name="Lexoh.Droid" expanded="True" />
          </Node>
        </State>
      </Pad>
      <Pad Id="MonoDevelop.Debugger.WatchPad">
        <State />
      </Pad>
    </Pads>
  </MonoDevelop.Ide.Workbench>
  <MonoDevelop.Ide.DebuggingService.Breakpoints>
    <BreakpointStore />
  </MonoDevelop.Ide.DebuggingService.Breakpoints>
  <MonoDevelop.MonoDroid LastDeploySdkVersion="13.0.0.0" />
  <Xamarin.Addins.Core.Project ActiveDebugTarget="Android.pixel_5_-_api_31" />
  <MonoDevelop.Ide.DebuggingService.PinnedWatches />
</Properties>